keystone/__init__.py
keystone/validator.py
keystone_license-0.1.2.dist-info/METADATA
keystone_license-0.1.2.dist-info/WHEEL
keystone_license-0.1.2.dist-info/top_level.txt
keystone_license-0.1.2.dist-info/RECORD
